MANIFEST.in
README.md
requirements.txt
setup.cfg
setup.py
ruin/__init__.py
ruin.egg-info/PKG-INFO
ruin.egg-info/SOURCES.txt
ruin.egg-info/dependency_links.txt
ruin.egg-info/requires.txt
ruin.egg-info/top_level.txt
ruin/db/__init__.py
ruin/db/connection.py
ruin/db/decorators.py
ruin/db/mongo_proxy.py
ruin/db/query_options.py
ruin/io/__init__.py
ruin/io/encoders.py
ruin/io/query_parser.py
ruin/io/slug.py
ruin/io/utils.py
ruin/io/validator.py
ruin/managers/__init__.py
ruin/managers/base.py
ruin/models/__init__.py
ruin/models/base.py