Metadata-Version: 1.1
Name: ruin
Version: 0.2.11
Summary: RUIN - Python/Mongo query builder and model validator
Home-page: https://gitlab.com/g----/ruin
Author: g----
Author-email: gloob@krutt.org
License: UNKNOWN
Platform: UNKNOWN
Classifier: Programming Language :: Python :: 3
Classifier: Operating System :: OS Independent
